xaux/__init__.py
xaux/dev_tools/__init__.py
xaux/dev_tools/gh.py
xaux/dev_tools/package_manager.py
xaux/dev_tools/release_tools.py
xaux/fs/__init__.py
xaux/fs/afs.py
xaux/fs/eos.py
xaux/fs/eos_methods.py
xaux/fs/fs.py
xaux/fs/fs_methods.py
xaux/fs/io.py
xaux/fs/temp.py
xaux/general.py
xaux/tools/__init__.py
xaux/tools/class_property.py
xaux/tools/function_tools.py
xaux/tools/general_tools.py
xaux/tools/protectfile.py
xaux/tools/singleton.py
xaux-0.3.12.dist-info/METADATA
xaux-0.3.12.dist-info/WHEEL
xaux-0.3.12.dist-info/licenses/LICENSE
xaux-0.3.12.dist-info/licenses/NOTICE
xaux-0.3.12.dist-info/RECORD
