Metadata-Version: 2.4
Name: xaux
Version: 0.3.12
Summary: Support tools for Xsuite packages
License: Apache 2.0
License-File: LICENSE
License-File: NOTICE
Author: Frederik F. Van der Veken
Author-email: frederik@cern.ch
Requires-Python: >=3.8,<3.15
Classifier: License :: Other/Proprietary License
Classifier: Programming Language :: Python :: 3
Classifier: Programming Language :: Python :: 3.8
Classifier: Programming Language :: Python :: 3.9
Classifier: Programming Language :: Python :: 3.10
Classifier: Programming Language :: Python :: 3.11
Classifier: Programming Language :: Python :: 3.12
Classifier: Programming Language :: Python :: 3.13
Classifier: Programming Language :: Python :: 3.14
Provides-Extra: tests
